target_questions_generator_agent/__init__.py
target_questions_generator_agent/agent.py
target_questions_generator_agent/config.py
target_questions_generator_agent/constants.py
target_questions_generator_agent/models.py
target_questions_generator_agent/utils.py
target_questions_generator_agent-1.0.4.dist-info/METADATA
target_questions_generator_agent-1.0.4.dist-info/WHEEL
target_questions_generator_agent-1.0.4.dist-info/entry_points.txt
target_questions_generator_agent-1.0.4.dist-info/top_level.txt
target_questions_generator_agent-1.0.4.dist-info/RECORD
