Metadata-Version: 2.4
Name: target-questions-generator-agent
Version: 1.0.4
Summary: AI-powered agent for converting technical ML requirements into user-friendly questions
Author-email: StepFunction AI <rajesh@stepfunction.ai>
Maintainer-email: StepFunction AI <rajesh@stepfunction.ai>
License: MIT
Project-URL: Homepage, https://github.com/stepfnAI/target_questions_generator_agent
Project-URL: Documentation, https://github.com/stepfnAI/target_questions_generator_agent#readme
Project-URL: Repository, https://github.com/stepfnAI/target_questions_generator_agent.git
Project-URL: Bug Tracker, https://github.com/stepfnAI/target_questions_generator_agent/issues
Keywords: machine learning,question generation,AI,ML,automation,user interface
Classifier: Development Status :: 3 - Alpha
Classifier: Intended Audience :: Developers
Classifier: Intended Audience :: Science/Research
Classifier: License :: OSI Approved :: MIT License
Classifier: Programming Language :: Python :: 3
Classifier: Programming Language :: Python :: 3.9
Classifier: Programming Language :: Python :: 3.10
Classifier: Programming Language :: Python :: 3.11
Classifier: Topic :: Scientific/Engineering :: Artificial Intelligence
Classifier: Topic :: Scientific/Engineering :: Information Analysis
Requires-Python: >=3.11
Requires-Dist: sfn-blueprint>=0.7.4
Requires-Dist: pandas>=1.5.0
Requires-Dist: numpy>=1.21.0
Requires-Dist: pydantic>=2.0.0
Requires-Dist: scikit-learn>=1.5.2
Provides-Extra: dev
Requires-Dist: pytest>=7.0.0; extra == "dev"
Requires-Dist: pytest-cov>=4.0.0; extra == "dev"
Requires-Dist: pytest-asyncio>=0.20.0; extra == "dev"
Requires-Dist: black>=22.0.0; extra == "dev"
Requires-Dist: flake8>=5.0.0; extra == "dev"
Requires-Dist: mypy>=1.0.0; extra == "dev"
Provides-Extra: test
Requires-Dist: pytest>=7.0.0; extra == "test"
Requires-Dist: pytest-cov>=4.0.0; extra == "test"
Requires-Dist: pytest-asyncio>=0.20.0; extra == "test"
